agentforce_client.py
agentforce_mcp_server.py
session_manager.py
iflow_mcp_xlengelle_sf_agentforce_mcp_server-0.1.0.dist-info/METADATA
iflow_mcp_xlengelle_sf_agentforce_mcp_server-0.1.0.dist-info/WHEEL
iflow_mcp_xlengelle_sf_agentforce_mcp_server-0.1.0.dist-info/entry_points.txt
iflow_mcp_xlengelle_sf_agentforce_mcp_server-0.1.0.dist-info/RECORD
