Metadata-Version: 2.4
Name: iflow-mcp-xlengelle-sf-agentforce-mcp-server
Version: 0.1.0
Summary: MCP server for interacting with Salesforce Agentforce API
Requires-Python: >=3.10
Requires-Dist: httpx>=0.24.0
Requires-Dist: mcp>=1.2.0
Requires-Dist: python-dotenv>=1.0.0
